notr/__init__.py
notr/__main__.py
notr/cli.py
notr/config.py
notr/crypto.py
notr/db.py
notr/errors.py
notr/merge.py
notr/models.py
notr/progress.py
notr/secrets.py
notr/session.py
notr/storage.py
notr/sync.py
notr/backends/__init__.py
notr/backends/base.py
notr/backends/local.py
notr/backends/webdav.py
notr-1.1.0.dist-info/licenses/LICENSE
notr-1.1.0.dist-info/METADATA
notr-1.1.0.dist-info/WHEEL
notr-1.1.0.dist-info/entry_points.txt
notr-1.1.0.dist-info/top_level.txt
notr-1.1.0.dist-info/RECORD
