Metadata-Version: 2.4
Name: notr
Version: 1.1.0
Summary: Encrypted, extensible command line note app with sync backends
Author: Kim Schulz
License: MIT
Project-URL: Homepage, https://github.com/kimsul/notr
Project-URL: Issues, https://github.com/kimsul/notr/issues
Requires-Python: >=3.9
License-File: LICENSE
Requires-Dist: click>=8.1.7
Requires-Dist: rich>=13.7.1
Requires-Dist: rich-click>=1.7.4
Requires-Dist: cryptography>=42.0.5
Requires-Dist: httpx>=0.27.0
Requires-Dist: rapidfuzz>=3.9.1
Requires-Dist: keyring>=25.2.0
Requires-Dist: pydantic>=2.6.4
Provides-Extra: dev
Requires-Dist: pytest>=8.1.1; extra == "dev"
Requires-Dist: pytest-cov>=4.1.0; extra == "dev"
Dynamic: license-file
